bhbotlist/__init__.py
bhbotlist-2.0.0.dist-info/LICENSE.txt
bhbotlist-2.0.0.dist-info/METADATA
bhbotlist-2.0.0.dist-info/WHEEL
bhbotlist-2.0.0.dist-info/top_level.txt
bhbotlist-2.0.0.dist-info/RECORD
